abbr/__init__.py
abbr/__main__.py
abbr/clients.py
abbr/core.py
abbr/exitstatus.py
abbr/scrapers.py
abbr_cli-1.0.3.dist-info/LICENSE
abbr_cli-1.0.3.dist-info/METADATA
abbr_cli-1.0.3.dist-info/WHEEL
abbr_cli-1.0.3.dist-info/entry_points.txt
abbr_cli-1.0.3.dist-info/top_level.txt
abbr_cli-1.0.3.dist-info/RECORD
