Metadata-Version: 2.1
Name: abbr-cli
Version: 1.0.3
Summary: A command-line tool to look up abbreviations for terms (and the reverse).
Home-page: UNKNOWN
Author: Mustapha Hadid
Author-email: mustapha.hadeed@gmail.com
License: MIT
Project-URL: GitHub, https://github.com/mhadidg/abbr-cli
Platform: UNKNOWN
Classifier: Environment :: Console
Classifier: Development Status :: 5 - Production/Stable
Classifier: License :: OSI Approved :: Apache Software License
Classifier: Programming Language :: Python
Classifier: Programming Language :: Python :: 3 :: Only
Classifier: Intended Audience :: Education
Classifier: Intended Audience :: Developers
Classifier: Topic :: Software Development
Classifier: Topic :: Terminals
Classifier: Topic :: Utilities
Requires-Python: >=3.6
License-File: LICENSE
Requires-Dist: requests (>=2.22.0)
Requires-Dist: lxml (>=4.5.0)
Requires-Dist: docopt (>=0.6.2)
Requires-Dist: colorful (>=0.5.4)
Requires-Dist: setuptools
Requires-Dist: colorama (>=0.2.4) ; sys_platform == "win32"
Provides-Extra: dev
Requires-Dist: twine ; extra == 'dev'
Requires-Dist: wheel ; extra == 'dev'
Provides-Extra: test
